{
    "name": "Polus Precompute Volume Plugin",
    "version": "0.2.1",
    "title": "WIPP Widget",
    "description": "Everything you need to start a WIPP plugin.",
    "author": "Data Scientist (data.scientist@labshare.org)",
    "institution": "National Center for Advancing Translational Sciences, National Institutes of Health",
    "repository": "https://github.com/labshare/polus-plugins",
    "website": "https://ncats.nih.gov/preclinical/core/informatics",
    "citation": "",
    "containerId": "labshare/polus-precompute-volume-plugin:0.2.1",
    "inputs": [
      {
        "name": "inpDir",
        "description": "Input collection",
        "type": "collection",
        "options": null,
        "required": true
      },
      {
        "name": "imageType",
        "description": "Image or Segmentation",
        "type": "enum",
        "options": {
          "values": [
            "image",
            "segmentation"
          ]
        },
        "required": true
      },
      {
        "name": "imagePattern",
        "description": "Pattern of the images in Input",
        "type": "string",
        "options": null,
        "required": false
      },
      {
        "name": "mesh",
        "description": "Create meshes",
        "type": "boolean",
        "options": null,
        "required": true
      }
    ],
    "outputs": [
      {
        "name": "outDir",
        "description": "Precomputed output",
        "type": "pyramid",
        "options": null,
        "required": true
      }
    ],
    "ui": [
      {
        "key": "inputs.inpDir",
        "title": "Input collection: ",
        "description": "Collection name..."
      },
      {
        "key": "inputs.imageType",
        "title": "Image Type: ",
        "description": "Image or Segmentation?"
      },
      {
        "key": "inputs.mesh",
        "title": "Create meshes: ",
        "default": "false",
        "condition": "inputs.imageType==['segmentation']"
      },
      {
        "key": "inputs.imagepattern",
        "title": "Image Pattern: ",
        "description": "Pattern of images in input collection (image_r{rrr}_c{ccc}_z{zzz}.ome.tif). "
      }
    ]
  }
