{
    "name": "UMAP (Shared-Memory)",
    "version": "0.1.2",
    "title": "UMAP (Shared-Memory)",
    "description": "PCA Shared-Memory Code",
    "author": "Mahdi Maghrebi",
    "institution": "National Center for Advancing Translational Sciences, National Institutes of Health",
    "containerId": "labshare/polus-umap-plugin:0.1.2",
    "inputs": [
        {
            "name": "inputPath",
            "type": "csvCollection",
            "description": "Input csv File",
            "required": "True"
        },
        {
            "name": "K",
            "type": "number",
            "description": "The desired number of Nearest Neighbours to be computed",
            "required": "True"
        },
        {
            "name": "sampleRate",
            "type": "number",
            "description": "The rate at which to do sampling. This parameter plays a key role in the performance. This parameter is a trade-off between the performance and the accuracy of the results. Values closer to 1 provides more accurate results but the execution takes longer.",
            "required": "True"
        },
        {
            "name": "DimLowSpace",
            "type": "number",
            "description": "Dimension of Low-D Space",
            "required": "True"
        },
        {
            "name": "randomInitializing",
            "type": "boolean",
            "description": "Defining the Method for Initialization of data in low-D space",
            "required": "True"
        },
        {
            "name": "n_epochs",
            "type": "number",
            "description": "The number of training epochs",
            "required": "True"
        },
        {
            "name": "min_dist",
            "type": "number",
            "description": "The variable that controls how tight (to each other) the data are placed in Low-D space",
            "required": "True"
        },
        {
            "name": "distanceMetric",
            "type": "enum",
            "description": "The name of metric used to compute the distance",
            "required": "True"
        },
        {
            "name": "distanceV1",
            "type": "number",
            "description": "The optional input needed for computation of some metrics",
            "required": "False"
        },
        {
            "name": "distanceV2",
            "type": "number",
            "description": "The optional input needed for computation of some metrics",
            "required": "False"
        },
        {
            "name": "inputPathOptionalArray",
            "type": "csvCollection",
            "description": "The optional csv file representing a vector needed in computation of some metrics",
            "required": "False"
        }
    ],
    "outputs": [
        {
            "name": "outputPath",
            "type": "csvCollection",
            "description": "Full path of the output csv file"
        }
    ],
    "ui": [
        {
            "key": "inputs.inputPath",
            "title": "Input CSV collection",
            "description": "Name of the input CSV collection"
        },
        {
            "key": "inputs.K",
			"title": "K",
			"description": "The desired number of Nearest Neighbours to be computed"
        },
        {
            "key": "inputs.sampleRate",
            "title": "Sampling Rate",
            "description": "This parameter plays a key role in the performance. This parameter is a trade-off between the performance and the accuracy of the results. Values closer to 1 provides more accurate results but the execution takes longer."
        },
        {
            "key": "inputs.DimLowSpace",
            "title": "Dimension of Low-D Space"
        },
        {
            "key": "inputs.randomInitializing",
            "title": "Random Initialization",
            "description": "Whether to Use Random Data Initialization?"
        },
        {
            "key": "inputs.nEpochs",
            "title": "The number of training epochs"
        }
    ]
}
